[
  {
    "id": "2213231",
    "comp_id": "1204",
    "formatted_date": "07.04.2018",
    "season": "2017/2018",
    "week": "33",
    "venue": "Goodison Park (Liverpool)",
    "venue_id": "87988",
    "venue_city": "Liverpool",
    "status": "FT",
    "timer": "",
    "time": "11:30",
    "localteam_id": "9158",
    "localteam_name": "Everton",
    "localteam_score": "0",
    "visitorteam_id": "9249",
    "visitorteam_name": "Liverpool",
    "visitorteam_score": "0",
    "ht_score": "[0-0]",
    "ft_score": "[0-0]",
    "et_score": null,
    "penalty_local": null,
    "penalty_visitor": null,
    "events": [
      {
        "id": "24236221",
        "type": "subst",
        "minute": "57",
        "extra_min": "",
        "team": "localteam",
        "player": "I. Gueye",
        "player_id": "95907",
        "assist": "W. Rooney",
        "assist_id": "193",
        "result": ""
      },
      {
        "id": "24236222",
        "type": "subst",
        "minute": "61",
        "extra_min": "",
        "team": "localteam",
        "player": "D. Calvert-Lewin",
        "player_id": "326320",
        "assist": "Y. Bolasie",
        "assist_id": "71338",
        "result": ""
      },
      {
        "id": "24236223",
        "type": "subst",
        "minute": "68",
        "extra_min": "",
        "team": "visitorteam",
        "player": "A. Oxlade-Chamberlain",
        "player_id": "120695",
        "assist": "J. Milner",
        "assist_id": "2899",
        "result": ""
      },
      {
        "id": "24236224",
        "type": "subst",
        "minute": "74",
        "extra_min": "",
        "team": "visitorteam",
        "player": "R. Firmino",
        "player_id": "103265",
        "assist": "S. Mane",
        "assist_id": "201602",
        "result": ""
      },
      {
        "id": "24236225",
        "type": "subst",
        "minute": "80",
        "extra_min": "",
        "team": "localteam",
        "player": "B. Baningime",
        "player_id": "453276",
        "assist": "T. Davies",
        "assist_id": "387381",
        "result": ""
      },
      {
        "id": "24236226",
        "type": "subst",
        "minute": "89",
        "extra_min": "",
        "team": "visitorteam",
        "player": "T. Alexander-Arnold",
        "player_id": "376875",
        "assist": "D. Ings",
        "assist_id": "139523",
        "result": ""
      }
    ]
  },
  {
    "id": "2213227",
    "comp_id": "1204",
    "formatted_date": "07.04.2018",
    "season": "2017/2018",
    "week": "33",
    "venue": "Vitality Stadium (Bournemouth, Dorset)",
    "venue_id": "58227",
    "venue_city": "Bournemouth, Dorset",
    "status": "FT",
    "timer": "",
    "time": "14:00",
    "localteam_id": "9053",
    "localteam_name": "AFC Bournemouth",
    "localteam_score": "2",
    "visitorteam_id": "9127",
    "visitorteam_name": "Crystal Palace",
    "visitorteam_score": "2",
    "ht_score": "[0-0]",
    "ft_score": "[2-2]",
    "et_score": null,
    "penalty_local": null,
    "penalty_visitor": null,
    "events": [
      {
        "id": "24235511",
        "type": "goal",
        "minute": "47",
        "extra_min": "",
        "team": "visitorteam",
        "player": "L. Milivojevic",
        "player_id": "90657",
        "assist": "",
        "assist_id": "",
        "result": "[0-1]"
      },
      {
        "id": "24235512",
        "type": "subst",
        "minute": "62",
        "extra_min": "",
        "team": "localteam",
        "player": "L. Mousset",
        "player_id": "278717",
        "assist": "M. Pugh",
        "assist_id": "50754",
        "result": ""
      },
      {
        "id": "24235513",
        "type": "subst",
        "minute": "62",
        "extra_min": "",
        "team": "localteam",
        "player": "J. King",
        "player_id": "93432",
        "assist": "C. Wilson",
        "assist_id": "89009",
        "result": ""
      },
      {
        "id": "24235514",
        "type": "goal",
        "minute": "65",
        "extra_min": "",
        "team": "localteam",
        "player": "L. Mousset",
        "player_id": "278717",
        "assist": "R. Fraser",
        "assist_id": "159839",
        "result": "[1-1]"
      },
      {
        "id": "24235515",
        "type": "goal",
        "minute": "75",
        "extra_min": "",
        "team": "visitorteam",
        "player": "W. Zaha",
        "player_id": "123878",
        "assist": "A. Townsend",
        "assist_id": "75627",
        "result": "[1-2]"
      },
      {
        "id": "24235516",
        "type": "yellowcard",
        "minute": "76",
        "extra_min": "",
        "team": "localteam",
        "player": "D. Gosling",
        "player_id": "15647",
        "assist": "Foul",
        "assist_id": "",
        "result": ""
      },
      {
        "id": "24235517",
        "type": "subst",
        "minute": "80",
        "extra_min": "",
        "team": "localteam",
        "player": "A. Surman",
        "player_id": "15494",
        "assist": "L. Cook",
        "assist_id": "335184",
        "result": ""
      },
      {
        "id": "24235518",
        "type": "yellowcard",
        "minute": "82",
        "extra_min": "",
        "team": "localteam",
        "player": "S. Francis",
        "player_id": "51102",
        "assist": "Tripping",
        "assist_id": "",
        "result": ""
      },
      {
        "id": "24235519",
        "type": "goal",
        "minute": "89",
        "extra_min": "",
        "team": "localteam",
        "player": "J. King",
        "player_id": "93432",
        "assist": "S. Cook",
        "assist_id": "139545",
        "result": "[2-2]"
      },
      {
        "id": "242355110",
        "type": "yellowcard",
        "minute": "90",
        "extra_min": "3",
        "team": "visitorteam",
        "player": "J. Tomkins",
        "player_id": "23292",
        "assist": "Tripping",
        "assist_id": "",
        "result": ""
      }
    ]
  },
  {
    "id": "2213229",
    "comp_id": "1204",
    "formatted_date": "07.04.2018",
    "season": "2017/2018",
    "week": "33",
    "venue": "The American Express Community Stadium (Falmer, East Sussex)",
    "venue_id": "86109",
    "venue_city": "Falmer, East Sussex",
    "status": "FT",
    "timer": "",
    "time": "14:00",
    "localteam_id": "9065",
    "localteam_name": "Brighton & Hove Albion",
    "localteam_score": "1",
    "visitorteam_id": "9220",
    "visitorteam_name": "Huddersfield Town",
    "visitorteam_score": "1",
    "ht_score": "[1-1]",
    "ft_score": "[1-1]",
    "et_score": null,
    "penalty_local": null,
    "penalty_visitor": null,
    "events": [
      {
        "id": "24235921",
        "type": "goal",
        "minute": "29",
        "extra_min": "",
        "team": "localteam",
        "player": "J. Lossl (o.g.)",
        "player_id": "39888",
        "assist": "",
        "assist_id": "",
        "result": "[1-0]"
      },
      {
        "id": "24235922",
        "type": "goal",
        "minute": "33",
        "extra_min": "",
        "team": "visitorteam",
        "player": "S. Mounie",
        "player_id": "249283",
        "assist": "",
        "assist_id": "",
        "result": "[1-1]"
      },
      {
        "id": "24235923",
        "type": "yellowcard",
        "minute": "58",
        "extra_min": "",
        "team": "localteam",
        "player": "S. Duffy",
        "player_id": "90884",
        "assist": "Tripping",
        "assist_id": "",
        "result": ""
      },
      {
        "id": "24235924",
        "type": "subst",
        "minute": "67",
        "extra_min": "",
        "team": "localteam",
        "player": "L. Ulloa",
        "player_id": "58861",
        "assist": "G. Murray",
        "assist_id": "50816",
        "result": ""
      },
      {
        "id": "24235925",
        "type": "redcard",
        "minute": "74",
        "extra_min": "",
        "team": "localteam",
        "player": "D. Propper",
        "player_id": "86220",
        "assist": "Foul",
        "assist_id": "",
        "result": ""
      },
      {
        "id": "24235926",
        "type": "subst",
        "minute": "76",
        "extra_min": "",
        "team": "localteam",
        "player": "B. Kayal",
        "player_id": "60290",
        "assist": "P. Gross",
        "assist_id": "78198",
        "result": ""
      },
      {
        "id": "24235927",
        "type": "subst",
        "minute": "80",
        "extra_min": "",
        "team": "visitorteam",
        "player": "P. Billing",
        "player_id": "335778",
        "assist": "J. Hogg",
        "assist_id": "89064",
        "result": ""
      },
      {
        "id": "24235928",
        "type": "subst",
        "minute": "90",
        "extra_min": "",
        "team": "visitorteam",
        "player": "C. Quaner",
        "player_id": "131801",
        "assist": "R. van La Parra",
        "assist_id": "39283",
        "result": ""
      },
      {
        "id": "24235929",
        "type": "subst",
        "minute": "90",
        "extra_min": "3",
        "team": "visitorteam",
        "player": "L. Depoitre",
        "player_id": "92514",
        "assist": "T. Ince",
        "assist_id": "138486",
        "result": ""
      }
    ]
  },
  {
    "id": "2213232",
    "comp_id": "1204",
    "formatted_date": "07.04.2018",
    "season": "2017/2018",
    "week": "33",
    "venue": "King Power Stadium (Leicester, Leicestershire)",
    "venue_id": "11632",
    "venue_city": "Leicester, Leicestershire",
    "status": "FT",
    "timer": "",
    "time": "14:00",
    "localteam_id": "9240",
    "localteam_name": "Leicester City",
    "localteam_score": "1",
    "visitorteam_id": "9287",
    "visitorteam_name": "Newcastle United",
    "visitorteam_score": "2",
    "ht_score": "[0-1]",
    "ft_score": "[1-2]",
    "et_score": null,
    "penalty_local": null,
    "penalty_visitor": null,
    "events": [
      {
        "id": "24235831",
        "type": "goal",
        "minute": "18",
        "extra_min": "",
        "team": "visitorteam",
        "player": "J. Shelvey",
        "player_id": "51243",
        "assist": "A. Perez",
        "assist_id": "262852",
        "result": "[0-1]"
      },
      {
        "id": "24235832",
        "type": "yellowcard",
        "minute": "21",
        "extra_min": "",
        "team": "localteam",
        "player": "H. Maguire",
        "player_id": "182047",
        "assist": "Roughing",
        "assist_id": "",
        "result": ""
      },
      {
        "id": "24235833",
        "type": "yellowcard",
        "minute": "21",
        "extra_min": "",
        "team": "visitorteam",
        "player": "J. Lascelles",
        "player_id": "192421",
        "assist": "Holding",
        "assist_id": "",
        "result": ""
      },
      {
        "id": "24235834",
        "type": "subst",
        "minute": "42",
        "extra_min": "",
        "team": "localteam",
        "player": "H. Choudhury",
        "player_id": "437092",
        "assist": "Iborra",
        "assist_id": "21190",
        "result": ""
      },
      {
        "id": "24235835",
        "type": "yellowcard",
        "minute": "52",
        "extra_min": "",
        "team": "visitorteam",
        "player": "D. Gayle",
        "player_id": "201233",
        "assist": "Tripping",
        "assist_id": "",
        "result": ""
      },
      {
        "id": "24235836",
        "type": "yellowcard",
        "minute": "55",
        "extra_min": "",
        "team": "visitorteam",
        "player": "M. Ritchie",
        "player_id": "65142",
        "assist": "Tripping",
        "assist_id": "",
        "result": ""
      },
      {
        "id": "24235837",
        "type": "subst",
        "minute": "57",
        "extra_min": "",
        "team": "localteam",
        "player": "S. Okazaki",
        "player_id": "5724",
        "assist": "D. Simpson",
        "assist_id": "20278",
        "result": ""
      },
      {
        "id": "24235838",
        "type": "subst",
        "minute": "64",
        "extra_min": "",
        "team": "visitorteam",
        "player": "C. Atsu",
        "player_id": "190602",
        "assist": "Kenedy",
        "assist_id": "287912",
        "result": ""
      },
      {
        "id": "24235839",
        "type": "subst",
        "minute": "70",
        "extra_min": "",
        "team": "visitorteam",
        "player": "Joselu",
        "player_id": "78568",
        "assist": "D. Gayle",
        "assist_id": "201233",
        "result": ""
      },
      {
        "id": "242358310",
        "type": "goal",
        "minute": "75",
        "extra_min": "",
        "team": "visitorteam",
        "player": "A. Perez",
        "player_id": "262852",
        "assist": "F. Lejeune",
        "assist_id": "112529",
        "result": "[0-2]"
      },
      {
        "id": "242358311",
        "type": "subst",
        "minute": "76",
        "extra_min": "",
        "team": "localteam",
        "player": "D. Gray",
        "player_id": "317144",
        "assist": "F. Diabate",
        "assist_id": "311892",
        "result": ""
      },
      {
        "id": "242358312",
        "type": "subst",
        "minute": "81",
        "extra_min": "",
        "team": "visitorteam",
        "player": "I. Hayden",
        "player_id": "215545",
        "assist": "M. Diame",
        "assist_id": "58677",
        "result": ""
      },
      {
        "id": "242358313",
        "type": "goal",
        "minute": "84",
        "extra_min": "",
        "team": "localteam",
        "player": "J. Vardy",
        "player_id": "159732",
        "assist": "S. Okazaki",
        "assist_id": "5724",
        "result": "[1-2]"
      }
    ]
  },
  {
    "id": "2213234",
    "comp_id": "1204",
    "formatted_date": "07.04.2018",
    "season": "2017/2018",
    "week": "33",
    "venue": "Bet365 Stadium (Stoke-on-Trent, Staffordshire)",
    "venue_id": "82581",
    "venue_city": "Stoke-on-Trent, Staffordshire",
    "status": "FT",
    "timer": "",
    "time": "14:00",
    "localteam_id": "9378",
    "localteam_name": "Stoke City",
    "localteam_score": "1",
    "visitorteam_id": "9406",
    "visitorteam_name": "Tottenham Hotspur",
    "visitorteam_score": "2",
    "ht_score": "[0-0]",
    "ft_score": "[1-2]",
    "et_score": null,
    "penalty_local": null,
    "penalty_visitor": null,
    "events": [
      {
        "id": "24235481",
        "type": "yellowcard",
        "minute": "32",
        "extra_min": "",
        "team": "localteam",
        "player": "E. Pieters",
        "player_id": "2487",
        "assist": "Tripping",
        "assist_id": "",
        "result": ""
      },
      {
        "id": "24235482",
        "type": "goal",
        "minute": "52",
        "extra_min": "",
        "team": "visitorteam",
        "player": "C. Eriksen",
        "player_id": "95871",
        "assist": "D. Alli",
        "assist_id": "217739",
        "result": "[0-1]"
      },
      {
        "id": "24235483",
        "type": "goal",
        "minute": "57",
        "extra_min": "",
        "team": "localteam",
        "player": "M. Diouf",
        "player_id": "28948",
        "assist": "",
        "assist_id": "",
        "result": "[1-1]"
      },
      {
        "id": "24235484",
        "type": "goal",
        "minute": "63",
        "extra_min": "",
        "team": "visitorteam",
        "player": "H. Kane",
        "player_id": "158575",
        "assist": "C. Eriksen",
        "assist_id": "95871",
        "result": "[1-2]"
      },
      {
        "id": "24235485",
        "type": "subst",
        "minute": "67",
        "extra_min": "",
        "team": "visitorteam",
        "player": "E. Lamela",
        "player_id": "81992",
        "assist": "Son Heung-Min",
        "assist_id": "103043",
        "result": ""
      },
      {
        "id": "24235486",
        "type": "subst",
        "minute": "69",
        "extra_min": "",
        "team": "localteam",
        "player": "T. Campbell",
        "player_id": "422456",
        "assist": "R. Sobhi",
        "assist_id": "346587",
        "result": ""
      },
      {
        "id": "24235487",
        "type": "yellowcard",
        "minute": "71",
        "extra_min": "",
        "team": "localteam",
        "player": "G. Johnson",
        "player_id": "2641",
        "assist": "Tripping",
        "assist_id": "",
        "result": ""
      },
      {
        "id": "24235488",
        "type": "subst",
        "minute": "78",
        "extra_min": "",
        "team": "localteam",
        "player": "P. Crouch",
        "player_id": "191",
        "assist": "G. Johnson",
        "assist_id": "2641",
        "result": ""
      },
      {
        "id": "24235489",
        "type": "yellowcard",
        "minute": "79",
        "extra_min": "",
        "team": "visitorteam",
        "player": "S. Aurier",
        "player_id": "155098",
        "assist": "Foul",
        "assist_id": "",
        "result": ""
      },
      {
        "id": "242354810",
        "type": "subst",
        "minute": "82",
        "extra_min": "",
        "team": "visitorteam",
        "player": "E. Dier",
        "player_id": "245831",
        "assist": "V. Wanyama",
        "assist_id": "53437",
        "result": ""
      },
      {
        "id": "242354811",
        "type": "subst",
        "minute": "89",
        "extra_min": "",
        "team": "visitorteam",
        "player": "M. Sissoko",
        "player_id": "13622",
        "assist": "D. Alli",
        "assist_id": "217739",
        "result": ""
      },
      {
        "id": "242354812",
        "type": "yellowcard",
        "minute": "90",
        "extra_min": "3",
        "team": "localteam",
        "player": "B. Martins Indi",
        "player_id": "102888",
        "assist": "Unsportsmanlike cond",
        "assist_id": "",
        "result": ""
      },
      {
        "id": "242354813",
        "type": "yellowcard",
        "minute": "90",
        "extra_min": "5",
        "team": "visitorteam",
        "player": "H. Kane",
        "player_id": "158575",
        "assist": "Foul",
        "assist_id": "",
        "result": ""
      },
      {
        "id": "242354814",
        "type": "subst",
        "minute": "90",
        "extra_min": "5",
        "team": "localteam",
        "player": "K. Zouma",
        "player_id": "162511",
        "assist": "M. Bauer",
        "assist_id": "195355",
        "result": ""
      },
      {
        "id": "242354815",
        "type": "yellowcard",
        "minute": "90",
        "extra_min": "8",
        "team": "localteam",
        "player": "P. Ndiaye",
        "player_id": "237612",
        "assist": "Unsportsmanlike cond",
        "assist_id": "",
        "result": ""
      },
      {
        "id": "242354816",
        "type": "yellowcard",
        "minute": "90",
        "extra_min": "8",
        "team": "visitorteam",
        "player": "D. Rose",
        "player_id": "187374",
        "assist": "Unsportsmanlike cond",
        "assist_id": "",
        "result": ""
      }
    ]
  }
]